drf_rbac/__init__.py
drf_rbac/mixins.py
drf_rbac/test.py
drf_rbac-0.1.dist-info/LICENSE
drf_rbac-0.1.dist-info/METADATA
drf_rbac-0.1.dist-info/WHEEL
drf_rbac-0.1.dist-info/top_level.txt
drf_rbac-0.1.dist-info/RECORD
