Metadata-Version: 2.1
Name: drf-rbac
Version: 0.1
Summary: Django rest framework user based access control.
Home-page: https://github.com/jtao15/drf-rbac
Author: Jiapeng Tao
Author-email: jiapengtao0@gmail.com
License: UNKNOWN
Platform: UNKNOWN
Classifier: Programming Language :: Python :: 3
Classifier: Operating System :: OS Independent
